cmeta/__init__.py
cmeta/__main__.py
cmeta/category.py
cmeta/category_api_v1.py
cmeta/cli.py
cmeta/config.py
cmeta/core.py
cmeta/core_async.py
cmeta/packages.py
cmeta/repos.py
cmeta/version.py
cmeta/internal-repo/_cmr.yaml
cmeta/internal-repo/app/cserver/_cmeta.yaml
cmeta/internal-repo/app/cserver/_run.bat
cmeta/internal-repo/app/cserver/_run.sh
cmeta/internal-repo/app/cserver/cserver.ico
cmeta/internal-repo/app/cserver/requirements.txt
cmeta/internal-repo/app/cserver/src/app.py
cmeta/internal-repo/app/cserver/src/static/images/favicon.ico
cmeta/internal-repo/app/cserver/src/static/js/cmeta_server.js
cmeta/internal-repo/app/cserver/src/templates/about.html
cmeta/internal-repo/app/cserver/src/templates/base.html
cmeta/internal-repo/app/cserver/src/templates/error.html
cmeta/internal-repo/app/cserver/src/templates/task.html
cmeta/internal-repo/category/app/_cmeta.yaml
cmeta/internal-repo/category/app/api/v1.py
cmeta/internal-repo/category/cache/_cmeta.yaml
cmeta/internal-repo/category/cache/api/v1.py
cmeta/internal-repo/category/category/_cmeta.yaml
cmeta/internal-repo/category/category/v1-template.py
cmeta/internal-repo/category/category/api/v1.py
cmeta/internal-repo/category/config/_cmeta.yaml
cmeta/internal-repo/category/config/api/v1.py
cmeta/internal-repo/category/docs/_cmeta.yaml
cmeta/internal-repo/category/docs/api/v1.py
cmeta/internal-repo/category/experiment/_cmeta.yaml
cmeta/internal-repo/category/experiment/api/v1.py
cmeta/internal-repo/category/journal/_cmeta.yaml
cmeta/internal-repo/category/journal/api/v1.py
cmeta/internal-repo/category/log/_cmeta.yaml
cmeta/internal-repo/category/log/api/v1.py
cmeta/internal-repo/category/note/_cmeta.yaml
cmeta/internal-repo/category/note/api/v1.py
cmeta/internal-repo/category/repo/_cmeta.yaml
cmeta/internal-repo/category/repo/api/common.py
cmeta/internal-repo/category/repo/api/v1.py
cmeta/internal-repo/category/report/_cmeta.yaml
cmeta/internal-repo/category/report/api/v1.py
cmeta-0.19.1.dist-info/licenses/COPYRIGHT
cmeta-0.19.1.dist-info/licenses/LICENSE
cmeta-0.19.1.dist-info/METADATA
cmeta-0.19.1.dist-info/WHEEL
cmeta-0.19.1.dist-info/entry_points.txt
cmeta-0.19.1.dist-info/top_level.txt
cmeta-0.19.1.dist-info/RECORD
