Metadata-Version: 2.4
Name: cmeta
Version: 0.19.1
Summary: cMeta (aka cX) is a common meta-framework for unifying, interconnecting and reusing code, data, models, agents, and knowledge across projects and domains.
Author: cTuning Labs
Author-email: Grigori Fursin <gfursin@ctuninglabs.com>
License-Expression: Apache-2.0
Classifier: Development Status :: 4 - Beta
Classifier: Intended Audience :: Developers
Classifier: Programming Language :: Python :: 3
Classifier: Programming Language :: Python :: 3.9
Classifier: Programming Language :: Python :: 3.10
Classifier: Programming Language :: Python :: 3.11
Classifier: Programming Language :: Python :: 3.12
Classifier: Programming Language :: Python :: 3.13
Classifier: Programming Language :: Python :: 3.14
Requires-Python: >=3.9
License-File: LICENSE
License-File: COPYRIGHT
Requires-Dist: pyyaml
Requires-Dist: requests
Requires-Dist: setuptools
Requires-Dist: wheel
Requires-Dist: tabulate
Requires-Dist: tqdm
Requires-Dist: filelock
Requires-Dist: packaging
Requires-Dist: psutil
Provides-Extra: dev
Requires-Dist: pytest>=6.0; extra == "dev"
Requires-Dist: pytest-cov; extra == "dev"
Requires-Dist: flake8; extra == "dev"
Provides-Extra: async
Requires-Dist: asyncio; extra == "async"
Provides-Extra: server
Requires-Dist: fastapi; extra == "server"
Requires-Dist: uvicorn; extra == "server"
Requires-Dist: jinja2; extra == "server"
Requires-Dist: starlette; extra == "server"
Requires-Dist: itsdangerous; extra == "server"
Requires-Dist: cmeta[async]; extra == "server"
Provides-Extra: all
Requires-Dist: cmeta[async,dev,server]; extra == "all"
Dynamic: license-file
